alouette/random.py
alouette/tauola.py
alouette/__main__.py
alouette/core.py
alouette/__init__.py
alouette/_core.abi3.so
alouette/version.py
alouette/include/alouette.h
alouette/include/tauola.h
alouette/lib/libalouette.so
alouette-1.0.1.dist-info/LICENSE
alouette-1.0.1.dist-info/COPYING.LESSER
alouette-1.0.1.dist-info/METADATA
alouette-1.0.1.dist-info/top_level.txt
alouette-1.0.1.dist-info/RECORD
alouette-1.0.1.dist-info/entry_points.txt
alouette-1.0.1.dist-info/WHEEL
