Metadata-Version: 2.1
Name: alouette
Version: 1.0.1
Summary: A TAUOLA wrapper with backward decays
Home-page: https://github.com/niess/alouette
Download-URL: https://pypi.python.org/pypi/alouette
Author: Valentin Niess
Author-email: valentin.niess@gmail.com
License: GPLv3
Project-URL: Bug Tracker, https://github.com/niess/alouette/issues
Project-URL: Source Code, https://github.com/niess/alouette
Platform: Linux
Classifier: Development Status :: 4 - Beta
Classifier: Intended Audience :: Science/Research
Classifier: License :: OSI Approved :: GNU Lesser General Public License v3 (LGPLv3)
Classifier: Programming Language :: Python
Classifier: Topic :: Scientific/Engineering :: Physics
Classifier: Operating System :: POSIX :: Linux
Requires-Python: >=3.6
License-File: LICENSE
License-File: COPYING.LESSER
Requires-Dist: cffi (>=1.0.0)
Requires-Dist: numpy
